odoo/addons/maintenance_timesheet_time_control/README.rst
odoo/addons/maintenance_timesheet_time_control/__init__.py
odoo/addons/maintenance_timesheet_time_control/__manifest__.py
odoo/addons/maintenance_timesheet_time_control/i18n/es.po
odoo/addons/maintenance_timesheet_time_control/i18n/fr.po
odoo/addons/maintenance_timesheet_time_control/i18n/it.po
odoo/addons/maintenance_timesheet_time_control/i18n/maintenance_timesheet_time_control.pot
odoo/addons/maintenance_timesheet_time_control/models/__init__.py
odoo/addons/maintenance_timesheet_time_control/models/maintenance_request.py
odoo/addons/maintenance_timesheet_time_control/readme/CONTRIBUTORS.rst
odoo/addons/maintenance_timesheet_time_control/readme/DESCRIPTION.rst
odoo/addons/maintenance_timesheet_time_control/readme/INSTALL.rst
odoo/addons/maintenance_timesheet_time_control/readme/USAGE.rst
odoo/addons/maintenance_timesheet_time_control/static/description/icon.png
odoo/addons/maintenance_timesheet_time_control/static/description/index.html
odoo/addons/maintenance_timesheet_time_control/tests/__init__.py
odoo/addons/maintenance_timesheet_time_control/tests/test_maintenance_timesheet_time_control.py
odoo/addons/maintenance_timesheet_time_control/views/maintenance_request_view.xml
odoo/addons/maintenance_timesheet_time_control/wizards/__init__.py
odoo/addons/maintenance_timesheet_time_control/wizards/hr_timesheet_switch.py
odoo14_addon_maintenance_timesheet_time_control-14.0.1.0.1.dev12.dist-info/METADATA
odoo14_addon_maintenance_timesheet_time_control-14.0.1.0.1.dev12.dist-info/WHEEL
odoo14_addon_maintenance_timesheet_time_control-14.0.1.0.1.dev12.dist-info/top_level.txt
odoo14_addon_maintenance_timesheet_time_control-14.0.1.0.1.dev12.dist-info/RECORD
